{"OriginStationID":"7090","OriginStationName":{"Zh_tw":"南澳","En":"Nan'ao"},"DestinationStationID":"3340","DestinationStationName":{"Zh_tw":"新烏日","En":"Xinwuri"},"Direction":1,"TrainType":7,"Fares":[{"TicketType":1,"FareClass":1,"CabinClass":1,"Price":325},{"TicketType":1,"FareClass":3,"CabinClass":1,"Price":163},{"TicketType":1,"FareClass":4,"CabinClass":1,"Price":163},{"TicketType":1,"FareClass":5,"CabinClass":1,"Price":163},{"TicketType":1,"FareClass":7,"CabinClass":1,"Price":163}],"TravelDistance":306.6}