{"OriginStationID":"6240","OriginStationName":{"Zh_tw":"志學","En":"Zhixue"},"DestinationStationID":"4340","DestinationStationName":{"Zh_tw":"新左營","En":"Xinzuoying"},"TrainFares":[{"TrainType":11,"Fares":[{"TicketType":1,"FareClass":1,"CabinClass":1,"Price":851},{"TicketType":1,"FareClass":3,"CabinClass":1,"Price":426},{"TicketType":1,"FareClass":4,"CabinClass":1,"Price":426},{"TicketType":1,"FareClass":5,"CabinClass":1,"Price":426},{"TicketType":1,"FareClass":7,"CabinClass":1,"Price":426}],"Direction":0},{"TrainType":1,"Fares":[{"TicketType":1,"FareClass":1,"CabinClass":1,"Price":851},{"TicketType":1,"FareClass":3,"CabinClass":1,"Price":426},{"TicketType":1,"FareClass":4,"CabinClass":1,"Price":426},{"TicketType":1,"FareClass":5,"CabinClass":1,"Price":426},{"TicketType":1,"FareClass":7,"CabinClass":1,"Price":426}],"Direction":0},{"TrainType":2,"Fares":[{"TicketType":1,"FareClass":1,"CabinClass":1,"Price":851},{"TicketType":1,"FareClass":3,"CabinClass":1,"Price":426},{"TicketType":1,"FareClass":4,"CabinClass":1,"Price":426},{"TicketType":1,"FareClass":5,"CabinClass":1,"Price":426},{"TicketType":1,"FareClass":7,"CabinClass":1,"Price":426}],"Direction":0},{"TrainType":3,"Fares":[{"TicketType":1,"FareClass":1,"CabinClass":1,"Price":851},{"TicketType":1,"FareClass":3,"CabinClass":1,"Price":426},{"TicketType":1,"FareClass":4,"CabinClass":1,"Price":426},{"TicketType":1,"FareClass":5,"CabinClass":1,"Price":426},{"TicketType":1,"FareClass":7,"CabinClass":1,"Price":426}],"Direction":0},{"TrainType":4,"Fares":[{"TicketType":1,"FareClass":1,"CabinClass":1,"Price":657},{"TicketType":1,"FareClass":3,"CabinClass":1,"Price":329},{"TicketType":1,"FareClass":4,"CabinClass":1,"Price":329},{"TicketType":1,"FareClass":5,"CabinClass":1,"Price":329},{"TicketType":1,"FareClass":7,"CabinClass":1,"Price":329}],"Direction":0},{"TrainType":5,"Fares":[{"TicketType":1,"FareClass":1,"CabinClass":1,"Price":548},{"TicketType":1,"FareClass":3,"CabinClass":1,"Price":274},{"TicketType":1,"FareClass":4,"CabinClass":1,"Price":274},{"TicketType":1,"FareClass":5,"CabinClass":1,"Price":274},{"TicketType":1,"FareClass":7,"CabinClass":1,"Price":274}],"Direction":0},{"TrainType":10,"Fares":[{"TicketType":1,"FareClass":1,"CabinClass":1,"Price":548},{"TicketType":1,"FareClass":3,"CabinClass":1,"Price":274},{"TicketType":1,"FareClass":4,"CabinClass":1,"Price":274},{"TicketType":1,"FareClass":5,"CabinClass":1,"Price":274},{"TicketType":1,"FareClass":7,"CabinClass":1,"Price":274}],"Direction":0},{"TrainType":6,"Fares":[{"TicketType":1,"FareClass":1,"CabinClass":1,"Price":548},{"TicketType":1,"FareClass":3,"CabinClass":1,"Price":274},{"TicketType":1,"FareClass":4,"CabinClass":1,"Price":274},{"TicketType":1,"FareClass":5,"CabinClass":1,"Price":274},{"TicketType":1,"FareClass":7,"CabinClass":1,"Price":274}],"Direction":0},{"TrainType":7,"Fares":[{"TicketType":1,"FareClass":1,"CabinClass":1,"Price":325},{"TicketType":1,"FareClass":3,"CabinClass":1,"Price":163},{"TicketType":1,"FareClass":4,"CabinClass":1,"Price":163},{"TicketType":1,"FareClass":5,"CabinClass":1,"Price":163},{"TicketType":1,"FareClass":7,"CabinClass":1,"Price":163}],"Direction":0},{"TrainType":11,"Fares":[{"TicketType":1,"FareClass":1,"CabinClass":1,"Price":1429},{"TicketType":1,"FareClass":3,"CabinClass":1,"Price":715},{"TicketType":1,"FareClass":4,"CabinClass":1,"Price":715},{"TicketType":1,"FareClass":5,"CabinClass":1,"Price":715},{"TicketType":1,"FareClass":7,"CabinClass":1,"Price":715}],"Direction":1},{"TrainType":1,"Fares":[{"TicketType":1,"FareClass":1,"CabinClass":1,"Price":1429},{"TicketType":1,"FareClass":3,"CabinClass":1,"Price":715},{"TicketType":1,"FareClass":4,"CabinClass":1,"Price":715},{"TicketType":1,"FareClass":5,"CabinClass":1,"Price":715},{"TicketType":1,"FareClass":7,"CabinClass":1,"Price":715}],"Direction":1},{"TrainType":2,"Fares":[{"TicketType":1,"FareClass":1,"CabinClass":1,"Price":1429},{"TicketType":1,"FareClass":3,"CabinClass":1,"Price":715},{"TicketType":1,"FareClass":4,"CabinClass":1,"Price":715},{"TicketType":1,"FareClass":5,"CabinClass":1,"Price":715},{"TicketType":1,"FareClass":7,"CabinClass":1,"Price":715}],"Direction":1},{"TrainType":3,"Fares":[{"TicketType":1,"FareClass":1,"CabinClass":1,"Price":1429},{"TicketType":1,"FareClass":3,"CabinClass":1,"Price":715},{"TicketType":1,"FareClass":4,"CabinClass":1,"Price":715},{"TicketType":1,"FareClass":5,"CabinClass":1,"Price":715},{"TicketType":1,"FareClass":7,"CabinClass":1,"Price":715}],"Direction":1},{"TrainType":4,"Fares":[{"TicketType":1,"FareClass":1,"CabinClass":1,"Price":1103},{"TicketType":1,"FareClass":3,"CabinClass":1,"Price":552},{"TicketType":1,"FareClass":4,"CabinClass":1,"Price":552},{"TicketType":1,"FareClass":5,"CabinClass":1,"Price":552},{"TicketType":1,"FareClass":7,"CabinClass":1,"Price":552}],"Direction":1},{"TrainType":5,"Fares":[{"TicketType":1,"FareClass":1,"CabinClass":1,"Price":922},{"TicketType":1,"FareClass":3,"CabinClass":1,"Price":461},{"TicketType":1,"FareClass":4,"CabinClass":1,"Price":461},{"TicketType":1,"FareClass":5,"CabinClass":1,"Price":461},{"TicketType":1,"FareClass":7,"CabinClass":1,"Price":461}],"Direction":1},{"TrainType":10,"Fares":[{"TicketType":1,"FareClass":1,"CabinClass":1,"Price":922},{"TicketType":1,"FareClass":3,"CabinClass":1,"Price":461},{"TicketType":1,"FareClass":4,"CabinClass":1,"Price":461},{"TicketType":1,"FareClass":5,"CabinClass":1,"Price":461},{"TicketType":1,"FareClass":7,"CabinClass":1,"Price":461}],"Direction":1},{"TrainType":6,"Fares":[{"TicketType":1,"FareClass":1,"CabinClass":1,"Price":922},{"TicketType":1,"FareClass":3,"CabinClass":1,"Price":461},{"TicketType":1,"FareClass":4,"CabinClass":1,"Price":461},{"TicketType":1,"FareClass":5,"CabinClass":1,"Price":461},{"TicketType":1,"FareClass":7,"CabinClass":1,"Price":461}],"Direction":1},{"TrainType":7,"Fares":[{"TicketType":1,"FareClass":1,"CabinClass":1,"Price":604},{"TicketType":1,"FareClass":3,"CabinClass":1,"Price":302},{"TicketType":1,"FareClass":4,"CabinClass":1,"Price":302},{"TicketType":1,"FareClass":5,"CabinClass":1,"Price":302},{"TicketType":1,"FareClass":7,"CabinClass":1,"Price":302}],"Direction":1}]}