{"OriginStationID":"3170","OriginStationName":{"Zh_tw":"南勢","En":"Nanshi"},"DestinationStationID":"5210","DestinationStationName":{"Zh_tw":"金崙","En":"Jinlun"},"Direction":1,"TrainType":7,"Fares":[{"TicketType":1,"FareClass":1,"CabinClass":1,"Price":400},{"TicketType":1,"FareClass":3,"CabinClass":1,"Price":200},{"TicketType":1,"FareClass":4,"CabinClass":1,"Price":200},{"TicketType":1,"FareClass":5,"CabinClass":1,"Price":200},{"TicketType":1,"FareClass":7,"CabinClass":1,"Price":200}],"TravelDistance":377.8}