{"OriginStationID":"2130","OriginStationName":{"Zh_tw":"後龍","En":"Houlong"},"DestinationStationID":"6190","DestinationStationName":{"Zh_tw":"南平","En":"Nanping"},"TrainFares":[{"TrainType":11,"Fares":[{"TicketType":1,"FareClass":1,"CabinClass":1,"Price":1206},{"TicketType":1,"FareClass":3,"CabinClass":1,"Price":603},{"TicketType":1,"FareClass":4,"CabinClass":1,"Price":603},{"TicketType":1,"FareClass":5,"CabinClass":1,"Price":603},{"TicketType":1,"FareClass":7,"CabinClass":1,"Price":603}]},{"TrainType":1,"Fares":[{"TicketType":1,"FareClass":1,"CabinClass":1,"Price":1206},{"TicketType":1,"FareClass":3,"CabinClass":1,"Price":603},{"TicketType":1,"FareClass":4,"CabinClass":1,"Price":603},{"TicketType":1,"FareClass":5,"CabinClass":1,"Price":603},{"TicketType":1,"FareClass":7,"CabinClass":1,"Price":603}]},{"TrainType":2,"Fares":[{"TicketType":1,"FareClass":1,"CabinClass":1,"Price":1206},{"TicketType":1,"FareClass":3,"CabinClass":1,"Price":603},{"TicketType":1,"FareClass":4,"CabinClass":1,"Price":603},{"TicketType":1,"FareClass":5,"CabinClass":1,"Price":603},{"TicketType":1,"FareClass":7,"CabinClass":1,"Price":603}]},{"TrainType":3,"Fares":[{"TicketType":1,"FareClass":1,"CabinClass":1,"Price":1206},{"TicketType":1,"FareClass":3,"CabinClass":1,"Price":603},{"TicketType":1,"FareClass":4,"CabinClass":1,"Price":603},{"TicketType":1,"FareClass":5,"CabinClass":1,"Price":603},{"TicketType":1,"FareClass":7,"CabinClass":1,"Price":603}]},{"TrainType":4,"Fares":[{"TicketType":1,"FareClass":1,"CabinClass":1,"Price":931},{"TicketType":1,"FareClass":3,"CabinClass":1,"Price":466},{"TicketType":1,"FareClass":4,"CabinClass":1,"Price":466},{"TicketType":1,"FareClass":5,"CabinClass":1,"Price":466},{"TicketType":1,"FareClass":7,"CabinClass":1,"Price":466}]},{"TrainType":5,"Fares":[{"TicketType":1,"FareClass":1,"CabinClass":1,"Price":778},{"TicketType":1,"FareClass":3,"CabinClass":1,"Price":389},{"TicketType":1,"FareClass":4,"CabinClass":1,"Price":389},{"TicketType":1,"FareClass":5,"CabinClass":1,"Price":389},{"TicketType":1,"FareClass":7,"CabinClass":1,"Price":389}]},{"TrainType":10,"Fares":[{"TicketType":1,"FareClass":1,"CabinClass":1,"Price":778},{"TicketType":1,"FareClass":3,"CabinClass":1,"Price":389},{"TicketType":1,"FareClass":4,"CabinClass":1,"Price":389},{"TicketType":1,"FareClass":5,"CabinClass":1,"Price":389},{"TicketType":1,"FareClass":7,"CabinClass":1,"Price":389}]},{"TrainType":6,"Fares":[{"TicketType":1,"FareClass":1,"CabinClass":1,"Price":778},{"TicketType":1,"FareClass":3,"CabinClass":1,"Price":389},{"TicketType":1,"FareClass":4,"CabinClass":1,"Price":389},{"TicketType":1,"FareClass":5,"CabinClass":1,"Price":389},{"TicketType":1,"FareClass":7,"CabinClass":1,"Price":389}]},{"TrainType":7,"Fares":[{"TicketType":1,"FareClass":1,"CabinClass":1,"Price":496},{"TicketType":1,"FareClass":3,"CabinClass":1,"Price":248},{"TicketType":1,"FareClass":4,"CabinClass":1,"Price":248},{"TicketType":1,"FareClass":5,"CabinClass":1,"Price":248},{"TicketType":1,"FareClass":7,"CabinClass":1,"Price":248}]}]}