{"OriginStationID":"1230","OriginStationName":{"Zh_tw":"香山","En":"Xiangshan"},"DestinationStationID":"7010","DestinationStationName":{"Zh_tw":"北埔","En":"Beipu"},"Direction":1,"TrainType":7,"Fares":[{"TicketType":1,"FareClass":1,"CabinClass":1,"Price":636},{"TicketType":1,"FareClass":3,"CabinClass":1,"Price":318},{"TicketType":1,"FareClass":4,"CabinClass":1,"Price":318},{"TicketType":1,"FareClass":5,"CabinClass":1,"Price":318},{"TicketType":1,"FareClass":7,"CabinClass":1,"Price":318}],"TravelDistance":600.1}