{"OriginStationID":"7300","OriginStationName":{"Zh_tw":"貢寮","En":"Gongliao"},"DestinationStationID":"1240","DestinationStationName":{"Zh_tw":"崎頂","En":"Qiding"},"Direction":1,"TrainType":7,"Fares":[{"TicketType":1,"FareClass":1,"CabinClass":1,"Price":154},{"TicketType":1,"FareClass":3,"CabinClass":1,"Price":77},{"TicketType":1,"FareClass":4,"CabinClass":1,"Price":77},{"TicketType":1,"FareClass":5,"CabinClass":1,"Price":77},{"TicketType":1,"FareClass":7,"CabinClass":1,"Price":77}],"TravelDistance":145.1}