{"OriginStationID":"3230","OriginStationName":{"Zh_tw":"豐原","En":"Fengyuan"},"DestinationStationID":"1201","DestinationStationName":{"Zh_tw":"上員","En":"Shangyuan"},"Direction":1,"TrainType":7,"Fares":[{"TicketType":1,"FareClass":1,"CabinClass":1,"Price":870},{"TicketType":1,"FareClass":3,"CabinClass":1,"Price":435},{"TicketType":1,"FareClass":4,"CabinClass":1,"Price":435},{"TicketType":1,"FareClass":5,"CabinClass":1,"Price":435},{"TicketType":1,"FareClass":7,"CabinClass":1,"Price":435}],"TravelDistance":811.3}