{"OriginStationID":"3390","OriginStationName":{"Zh_tw":"員林","En":"Yuanlin"},"DestinationStationID":"2240","DestinationStationName":{"Zh_tw":"龍井","En":"Longjing"},"TrainFares":[{"TrainType":11,"Fares":[{"TicketType":1,"FareClass":1,"CabinClass":1,"Price":108},{"TicketType":1,"FareClass":3,"CabinClass":1,"Price":54},{"TicketType":1,"FareClass":4,"CabinClass":1,"Price":54},{"TicketType":1,"FareClass":5,"CabinClass":1,"Price":54},{"TicketType":1,"FareClass":7,"CabinClass":1,"Price":54}]},{"TrainType":1,"Fares":[{"TicketType":1,"FareClass":1,"CabinClass":1,"Price":108},{"TicketType":1,"FareClass":3,"CabinClass":1,"Price":54},{"TicketType":1,"FareClass":4,"CabinClass":1,"Price":54},{"TicketType":1,"FareClass":5,"CabinClass":1,"Price":54},{"TicketType":1,"FareClass":7,"CabinClass":1,"Price":54}]},{"TrainType":2,"Fares":[{"TicketType":1,"FareClass":1,"CabinClass":1,"Price":108},{"TicketType":1,"FareClass":3,"CabinClass":1,"Price":54},{"TicketType":1,"FareClass":4,"CabinClass":1,"Price":54},{"TicketType":1,"FareClass":5,"CabinClass":1,"Price":54},{"TicketType":1,"FareClass":7,"CabinClass":1,"Price":54}]},{"TrainType":3,"Fares":[{"TicketType":1,"FareClass":1,"CabinClass":1,"Price":108},{"TicketType":1,"FareClass":3,"CabinClass":1,"Price":54},{"TicketType":1,"FareClass":4,"CabinClass":1,"Price":54},{"TicketType":1,"FareClass":5,"CabinClass":1,"Price":54},{"TicketType":1,"FareClass":7,"CabinClass":1,"Price":54}]},{"TrainType":4,"Fares":[{"TicketType":1,"FareClass":1,"CabinClass":1,"Price":83},{"TicketType":1,"FareClass":3,"CabinClass":1,"Price":42},{"TicketType":1,"FareClass":4,"CabinClass":1,"Price":42},{"TicketType":1,"FareClass":5,"CabinClass":1,"Price":42},{"TicketType":1,"FareClass":7,"CabinClass":1,"Price":42}]},{"TrainType":5,"Fares":[{"TicketType":1,"FareClass":1,"CabinClass":1,"Price":69},{"TicketType":1,"FareClass":3,"CabinClass":1,"Price":35},{"TicketType":1,"FareClass":4,"CabinClass":1,"Price":35},{"TicketType":1,"FareClass":5,"CabinClass":1,"Price":35},{"TicketType":1,"FareClass":7,"CabinClass":1,"Price":35}]},{"TrainType":10,"Fares":[{"TicketType":1,"FareClass":1,"CabinClass":1,"Price":69},{"TicketType":1,"FareClass":3,"CabinClass":1,"Price":35},{"TicketType":1,"FareClass":4,"CabinClass":1,"Price":35},{"TicketType":1,"FareClass":5,"CabinClass":1,"Price":35},{"TicketType":1,"FareClass":7,"CabinClass":1,"Price":35}]},{"TrainType":6,"Fares":[{"TicketType":1,"FareClass":1,"CabinClass":1,"Price":69},{"TicketType":1,"FareClass":3,"CabinClass":1,"Price":35},{"TicketType":1,"FareClass":4,"CabinClass":1,"Price":35},{"TicketType":1,"FareClass":5,"CabinClass":1,"Price":35},{"TicketType":1,"FareClass":7,"CabinClass":1,"Price":35}]},{"TrainType":7,"Fares":[{"TicketType":1,"FareClass":1,"CabinClass":1,"Price":34},{"TicketType":1,"FareClass":3,"CabinClass":1,"Price":17},{"TicketType":1,"FareClass":4,"CabinClass":1,"Price":17},{"TicketType":1,"FareClass":5,"CabinClass":1,"Price":17},{"TicketType":1,"FareClass":7,"CabinClass":1,"Price":17}]},{"TrainType":11,"Fares":[{"TicketType":1,"FareClass":1,"CabinClass":1,"Price":2044},{"TicketType":1,"FareClass":3,"CabinClass":1,"Price":1022},{"TicketType":1,"FareClass":4,"CabinClass":1,"Price":1022},{"TicketType":1,"FareClass":5,"CabinClass":1,"Price":1022},{"TicketType":1,"FareClass":7,"CabinClass":1,"Price":1022}]},{"TrainType":1,"Fares":[{"TicketType":1,"FareClass":1,"CabinClass":1,"Price":2044},{"TicketType":1,"FareClass":3,"CabinClass":1,"Price":1022},{"TicketType":1,"FareClass":4,"CabinClass":1,"Price":1022},{"TicketType":1,"FareClass":5,"CabinClass":1,"Price":1022},{"TicketType":1,"FareClass":7,"CabinClass":1,"Price":1022}]},{"TrainType":2,"Fares":[{"TicketType":1,"FareClass":1,"CabinClass":1,"Price":2044},{"TicketType":1,"FareClass":3,"CabinClass":1,"Price":1022},{"TicketType":1,"FareClass":4,"CabinClass":1,"Price":1022},{"TicketType":1,"FareClass":5,"CabinClass":1,"Price":1022},{"TicketType":1,"FareClass":7,"CabinClass":1,"Price":1022}]},{"TrainType":3,"Fares":[{"TicketType":1,"FareClass":1,"CabinClass":1,"Price":2044},{"TicketType":1,"FareClass":3,"CabinClass":1,"Price":1022},{"TicketType":1,"FareClass":4,"CabinClass":1,"Price":1022},{"TicketType":1,"FareClass":5,"CabinClass":1,"Price":1022},{"TicketType":1,"FareClass":7,"CabinClass":1,"Price":1022}]},{"TrainType":4,"Fares":[{"TicketType":1,"FareClass":1,"CabinClass":1,"Price":1578},{"TicketType":1,"FareClass":3,"CabinClass":1,"Price":789},{"TicketType":1,"FareClass":4,"CabinClass":1,"Price":789},{"TicketType":1,"FareClass":5,"CabinClass":1,"Price":789},{"TicketType":1,"FareClass":7,"CabinClass":1,"Price":789}]},{"TrainType":5,"Fares":[{"TicketType":1,"FareClass":1,"CabinClass":1,"Price":1318},{"TicketType":1,"FareClass":3,"CabinClass":1,"Price":659},{"TicketType":1,"FareClass":4,"CabinClass":1,"Price":659},{"TicketType":1,"FareClass":5,"CabinClass":1,"Price":659},{"TicketType":1,"FareClass":7,"CabinClass":1,"Price":659}]},{"TrainType":10,"Fares":[{"TicketType":1,"FareClass":1,"CabinClass":1,"Price":1318},{"TicketType":1,"FareClass":3,"CabinClass":1,"Price":659},{"TicketType":1,"FareClass":4,"CabinClass":1,"Price":659},{"TicketType":1,"FareClass":5,"CabinClass":1,"Price":659},{"TicketType":1,"FareClass":7,"CabinClass":1,"Price":659}]},{"TrainType":6,"Fares":[{"TicketType":1,"FareClass":1,"CabinClass":1,"Price":1318},{"TicketType":1,"FareClass":3,"CabinClass":1,"Price":659},{"TicketType":1,"FareClass":4,"CabinClass":1,"Price":659},{"TicketType":1,"FareClass":5,"CabinClass":1,"Price":659},{"TicketType":1,"FareClass":7,"CabinClass":1,"Price":659}]},{"TrainType":7,"Fares":[{"TicketType":1,"FareClass":1,"CabinClass":1,"Price":900},{"TicketType":1,"FareClass":3,"CabinClass":1,"Price":450},{"TicketType":1,"FareClass":4,"CabinClass":1,"Price":450},{"TicketType":1,"FareClass":5,"CabinClass":1,"Price":450},{"TicketType":1,"FareClass":7,"CabinClass":1,"Price":450}]}]}