{"OriginStationID":"1130","OriginStationName":{"Zh_tw":"富岡","En":"Fugang"},"DestinationStationID":"4180","DestinationStationName":{"Zh_tw":"南科","En":"Nanke"},"Direction":1,"TrainType":7,"Fares":[{"TicketType":1,"FareClass":1,"CabinClass":1,"Price":268},{"TicketType":1,"FareClass":3,"CabinClass":1,"Price":134},{"TicketType":1,"FareClass":4,"CabinClass":1,"Price":134},{"TicketType":1,"FareClass":5,"CabinClass":1,"Price":134},{"TicketType":1,"FareClass":7,"CabinClass":1,"Price":134}],"TravelDistance":253}