{"OriginStationID":"6130","OriginStationName":{"Zh_tw":"瑞穗","En":"Ruisui"},"DestinationStationID":"1208","DestinationStationName":{"Zh_tw":"內灣","En":"Neiwan"},"TrainFares":[{"TrainType":11,"Fares":[{"TicketType":1,"FareClass":1,"CabinClass":1,"Price":1427},{"TicketType":1,"FareClass":3,"CabinClass":1,"Price":714},{"TicketType":1,"FareClass":4,"CabinClass":1,"Price":714},{"TicketType":1,"FareClass":5,"CabinClass":1,"Price":714},{"TicketType":1,"FareClass":7,"CabinClass":1,"Price":714}],"Direction":0},{"TrainType":1,"Fares":[{"TicketType":1,"FareClass":1,"CabinClass":1,"Price":1427},{"TicketType":1,"FareClass":3,"CabinClass":1,"Price":714},{"TicketType":1,"FareClass":4,"CabinClass":1,"Price":714},{"TicketType":1,"FareClass":5,"CabinClass":1,"Price":714},{"TicketType":1,"FareClass":7,"CabinClass":1,"Price":714}],"Direction":0},{"TrainType":2,"Fares":[{"TicketType":1,"FareClass":1,"CabinClass":1,"Price":1427},{"TicketType":1,"FareClass":3,"CabinClass":1,"Price":714},{"TicketType":1,"FareClass":4,"CabinClass":1,"Price":714},{"TicketType":1,"FareClass":5,"CabinClass":1,"Price":714},{"TicketType":1,"FareClass":7,"CabinClass":1,"Price":714}],"Direction":0},{"TrainType":3,"Fares":[{"TicketType":1,"FareClass":1,"CabinClass":1,"Price":1427},{"TicketType":1,"FareClass":3,"CabinClass":1,"Price":714},{"TicketType":1,"FareClass":4,"CabinClass":1,"Price":714},{"TicketType":1,"FareClass":5,"CabinClass":1,"Price":714},{"TicketType":1,"FareClass":7,"CabinClass":1,"Price":714}],"Direction":0},{"TrainType":4,"Fares":[{"TicketType":1,"FareClass":1,"CabinClass":1,"Price":1115},{"TicketType":1,"FareClass":3,"CabinClass":1,"Price":558},{"TicketType":1,"FareClass":4,"CabinClass":1,"Price":558},{"TicketType":1,"FareClass":5,"CabinClass":1,"Price":558},{"TicketType":1,"FareClass":7,"CabinClass":1,"Price":558}],"Direction":0},{"TrainType":5,"Fares":[{"TicketType":1,"FareClass":1,"CabinClass":1,"Price":940},{"TicketType":1,"FareClass":3,"CabinClass":1,"Price":471},{"TicketType":1,"FareClass":4,"CabinClass":1,"Price":471},{"TicketType":1,"FareClass":5,"CabinClass":1,"Price":471},{"TicketType":1,"FareClass":7,"CabinClass":1,"Price":471}],"Direction":0},{"TrainType":10,"Fares":[{"TicketType":1,"FareClass":1,"CabinClass":1,"Price":940},{"TicketType":1,"FareClass":3,"CabinClass":1,"Price":471},{"TicketType":1,"FareClass":4,"CabinClass":1,"Price":471},{"TicketType":1,"FareClass":5,"CabinClass":1,"Price":471},{"TicketType":1,"FareClass":7,"CabinClass":1,"Price":471}],"Direction":0},{"TrainType":6,"Fares":[{"TicketType":1,"FareClass":1,"CabinClass":1,"Price":940},{"TicketType":1,"FareClass":3,"CabinClass":1,"Price":471},{"TicketType":1,"FareClass":4,"CabinClass":1,"Price":471},{"TicketType":1,"FareClass":5,"CabinClass":1,"Price":471},{"TicketType":1,"FareClass":7,"CabinClass":1,"Price":471}],"Direction":0},{"TrainType":7,"Fares":[{"TicketType":1,"FareClass":1,"CabinClass":1,"Price":632},{"TicketType":1,"FareClass":3,"CabinClass":1,"Price":317},{"TicketType":1,"FareClass":4,"CabinClass":1,"Price":317},{"TicketType":1,"FareClass":5,"CabinClass":1,"Price":317},{"TicketType":1,"FareClass":7,"CabinClass":1,"Price":317}],"Direction":0},{"TrainType":11,"Fares":[{"TicketType":1,"FareClass":1,"CabinClass":1,"Price":967},{"TicketType":1,"FareClass":3,"CabinClass":1,"Price":484},{"TicketType":1,"FareClass":4,"CabinClass":1,"Price":484},{"TicketType":1,"FareClass":5,"CabinClass":1,"Price":484},{"TicketType":1,"FareClass":7,"CabinClass":1,"Price":484}],"Direction":1},{"TrainType":1,"Fares":[{"TicketType":1,"FareClass":1,"CabinClass":1,"Price":967},{"TicketType":1,"FareClass":3,"CabinClass":1,"Price":484},{"TicketType":1,"FareClass":4,"CabinClass":1,"Price":484},{"TicketType":1,"FareClass":5,"CabinClass":1,"Price":484},{"TicketType":1,"FareClass":7,"CabinClass":1,"Price":484}],"Direction":1},{"TrainType":2,"Fares":[{"TicketType":1,"FareClass":1,"CabinClass":1,"Price":967},{"TicketType":1,"FareClass":3,"CabinClass":1,"Price":484},{"TicketType":1,"FareClass":4,"CabinClass":1,"Price":484},{"TicketType":1,"FareClass":5,"CabinClass":1,"Price":484},{"TicketType":1,"FareClass":7,"CabinClass":1,"Price":484}],"Direction":1},{"TrainType":3,"Fares":[{"TicketType":1,"FareClass":1,"CabinClass":1,"Price":967},{"TicketType":1,"FareClass":3,"CabinClass":1,"Price":484},{"TicketType":1,"FareClass":4,"CabinClass":1,"Price":484},{"TicketType":1,"FareClass":5,"CabinClass":1,"Price":484},{"TicketType":1,"FareClass":7,"CabinClass":1,"Price":484}],"Direction":1},{"TrainType":4,"Fares":[{"TicketType":1,"FareClass":1,"CabinClass":1,"Price":759},{"TicketType":1,"FareClass":3,"CabinClass":1,"Price":380},{"TicketType":1,"FareClass":4,"CabinClass":1,"Price":380},{"TicketType":1,"FareClass":5,"CabinClass":1,"Price":380},{"TicketType":1,"FareClass":7,"CabinClass":1,"Price":380}],"Direction":1},{"TrainType":5,"Fares":[{"TicketType":1,"FareClass":1,"CabinClass":1,"Price":644},{"TicketType":1,"FareClass":3,"CabinClass":1,"Price":323},{"TicketType":1,"FareClass":4,"CabinClass":1,"Price":323},{"TicketType":1,"FareClass":5,"CabinClass":1,"Price":323},{"TicketType":1,"FareClass":7,"CabinClass":1,"Price":323}],"Direction":1},{"TrainType":10,"Fares":[{"TicketType":1,"FareClass":1,"CabinClass":1,"Price":644},{"TicketType":1,"FareClass":3,"CabinClass":1,"Price":323},{"TicketType":1,"FareClass":4,"CabinClass":1,"Price":323},{"TicketType":1,"FareClass":5,"CabinClass":1,"Price":323},{"TicketType":1,"FareClass":7,"CabinClass":1,"Price":323}],"Direction":1},{"TrainType":6,"Fares":[{"TicketType":1,"FareClass":1,"CabinClass":1,"Price":644},{"TicketType":1,"FareClass":3,"CabinClass":1,"Price":323},{"TicketType":1,"FareClass":4,"CabinClass":1,"Price":323},{"TicketType":1,"FareClass":5,"CabinClass":1,"Price":323},{"TicketType":1,"FareClass":7,"CabinClass":1,"Price":323}],"Direction":1},{"TrainType":7,"Fares":[{"TicketType":1,"FareClass":1,"CabinClass":1,"Price":411},{"TicketType":1,"FareClass":3,"CabinClass":1,"Price":206},{"TicketType":1,"FareClass":4,"CabinClass":1,"Price":206},{"TicketType":1,"FareClass":5,"CabinClass":1,"Price":206},{"TicketType":1,"FareClass":7,"CabinClass":1,"Price":206}],"Direction":1}]}