{"OriginStationID":"7240","OriginStationName":{"Zh_tw":"外澳","En":"Wai'ao"},"DestinationStationID":"1180","DestinationStationName":{"Zh_tw":"竹北","En":"Zhubei"},"TrainFares":[{"TrainType":11,"Fares":[{"TicketType":1,"FareClass":1,"CabinClass":1,"Price":459},{"TicketType":1,"FareClass":3,"CabinClass":1,"Price":230},{"TicketType":1,"FareClass":4,"CabinClass":1,"Price":230},{"TicketType":1,"FareClass":5,"CabinClass":1,"Price":230},{"TicketType":1,"FareClass":7,"CabinClass":1,"Price":230}]},{"TrainType":1,"Fares":[{"TicketType":1,"FareClass":1,"CabinClass":1,"Price":459},{"TicketType":1,"FareClass":3,"CabinClass":1,"Price":230},{"TicketType":1,"FareClass":4,"CabinClass":1,"Price":230},{"TicketType":1,"FareClass":5,"CabinClass":1,"Price":230},{"TicketType":1,"FareClass":7,"CabinClass":1,"Price":230}]},{"TrainType":2,"Fares":[{"TicketType":1,"FareClass":1,"CabinClass":1,"Price":459},{"TicketType":1,"FareClass":3,"CabinClass":1,"Price":230},{"TicketType":1,"FareClass":4,"CabinClass":1,"Price":230},{"TicketType":1,"FareClass":5,"CabinClass":1,"Price":230},{"TicketType":1,"FareClass":7,"CabinClass":1,"Price":230}]},{"TrainType":3,"Fares":[{"TicketType":1,"FareClass":1,"CabinClass":1,"Price":459},{"TicketType":1,"FareClass":3,"CabinClass":1,"Price":230},{"TicketType":1,"FareClass":4,"CabinClass":1,"Price":230},{"TicketType":1,"FareClass":5,"CabinClass":1,"Price":230},{"TicketType":1,"FareClass":7,"CabinClass":1,"Price":230}]},{"TrainType":4,"Fares":[{"TicketType":1,"FareClass":1,"CabinClass":1,"Price":354},{"TicketType":1,"FareClass":3,"CabinClass":1,"Price":177},{"TicketType":1,"FareClass":4,"CabinClass":1,"Price":177},{"TicketType":1,"FareClass":5,"CabinClass":1,"Price":177},{"TicketType":1,"FareClass":7,"CabinClass":1,"Price":177}]},{"TrainType":5,"Fares":[{"TicketType":1,"FareClass":1,"CabinClass":1,"Price":295},{"TicketType":1,"FareClass":3,"CabinClass":1,"Price":148},{"TicketType":1,"FareClass":4,"CabinClass":1,"Price":148},{"TicketType":1,"FareClass":5,"CabinClass":1,"Price":148},{"TicketType":1,"FareClass":7,"CabinClass":1,"Price":148}]},{"TrainType":10,"Fares":[{"TicketType":1,"FareClass":1,"CabinClass":1,"Price":295},{"TicketType":1,"FareClass":3,"CabinClass":1,"Price":148},{"TicketType":1,"FareClass":4,"CabinClass":1,"Price":148},{"TicketType":1,"FareClass":5,"CabinClass":1,"Price":148},{"TicketType":1,"FareClass":7,"CabinClass":1,"Price":148}]},{"TrainType":6,"Fares":[{"TicketType":1,"FareClass":1,"CabinClass":1,"Price":295},{"TicketType":1,"FareClass":3,"CabinClass":1,"Price":148},{"TicketType":1,"FareClass":4,"CabinClass":1,"Price":148},{"TicketType":1,"FareClass":5,"CabinClass":1,"Price":148},{"TicketType":1,"FareClass":7,"CabinClass":1,"Price":148}]},{"TrainType":7,"Fares":[{"TicketType":1,"FareClass":1,"CabinClass":1,"Price":159},{"TicketType":1,"FareClass":3,"CabinClass":1,"Price":80},{"TicketType":1,"FareClass":4,"CabinClass":1,"Price":80},{"TicketType":1,"FareClass":5,"CabinClass":1,"Price":80},{"TicketType":1,"FareClass":7,"CabinClass":1,"Price":80}]}]}