{"OriginStationID":"7120","OriginStationName":{"Zh_tw":"蘇澳","En":"Su'ao"},"DestinationStationID":"6080","DestinationStationName":{"Zh_tw":"富里","En":"Fuli"},"Direction":1,"TrainType":7,"Fares":[{"TicketType":1,"FareClass":1,"CabinClass":1,"Price":740},{"TicketType":1,"FareClass":3,"CabinClass":1,"Price":370},{"TicketType":1,"FareClass":4,"CabinClass":1,"Price":370},{"TicketType":1,"FareClass":5,"CabinClass":1,"Price":370},{"TicketType":1,"FareClass":7,"CabinClass":1,"Price":370}],"TravelDistance":697.8}