{"OriginStationID":"7333","OriginStationName":{"Zh_tw":"望古","En":"Wanggu"},"DestinationStationID":"2260","DestinationStationName":{"Zh_tw":"追分","En":"Zhuifen"},"Direction":1,"TrainType":7,"Fares":[{"TicketType":1,"FareClass":1,"CabinClass":1,"Price":249},{"TicketType":1,"FareClass":3,"CabinClass":1,"Price":125},{"TicketType":1,"FareClass":4,"CabinClass":1,"Price":125},{"TicketType":1,"FareClass":5,"CabinClass":1,"Price":125},{"TicketType":1,"FareClass":7,"CabinClass":1,"Price":125}],"TravelDistance":226.2}