{"OriginStationID":"7333","OriginStationName":{"Zh_tw":"望古","En":"Wanggu"},"DestinationStationID":"6180","DestinationStationName":{"Zh_tw":"鳳林","En":"Fenglin"},"TrainFares":[{"TrainType":11,"Fares":[{"TicketType":1,"FareClass":1,"CabinClass":1,"Price":578},{"TicketType":1,"FareClass":3,"CabinClass":1,"Price":289},{"TicketType":1,"FareClass":4,"CabinClass":1,"Price":289},{"TicketType":1,"FareClass":5,"CabinClass":1,"Price":289},{"TicketType":1,"FareClass":7,"CabinClass":1,"Price":289}]},{"TrainType":1,"Fares":[{"TicketType":1,"FareClass":1,"CabinClass":1,"Price":578},{"TicketType":1,"FareClass":3,"CabinClass":1,"Price":289},{"TicketType":1,"FareClass":4,"CabinClass":1,"Price":289},{"TicketType":1,"FareClass":5,"CabinClass":1,"Price":289},{"TicketType":1,"FareClass":7,"CabinClass":1,"Price":289}]},{"TrainType":2,"Fares":[{"TicketType":1,"FareClass":1,"CabinClass":1,"Price":578},{"TicketType":1,"FareClass":3,"CabinClass":1,"Price":289},{"TicketType":1,"FareClass":4,"CabinClass":1,"Price":289},{"TicketType":1,"FareClass":5,"CabinClass":1,"Price":289},{"TicketType":1,"FareClass":7,"CabinClass":1,"Price":289}]},{"TrainType":3,"Fares":[{"TicketType":1,"FareClass":1,"CabinClass":1,"Price":578},{"TicketType":1,"FareClass":3,"CabinClass":1,"Price":289},{"TicketType":1,"FareClass":4,"CabinClass":1,"Price":289},{"TicketType":1,"FareClass":5,"CabinClass":1,"Price":289},{"TicketType":1,"FareClass":7,"CabinClass":1,"Price":289}]},{"TrainType":4,"Fares":[{"TicketType":1,"FareClass":1,"CabinClass":1,"Price":450},{"TicketType":1,"FareClass":3,"CabinClass":1,"Price":225},{"TicketType":1,"FareClass":4,"CabinClass":1,"Price":225},{"TicketType":1,"FareClass":5,"CabinClass":1,"Price":225},{"TicketType":1,"FareClass":7,"CabinClass":1,"Price":225}]},{"TrainType":5,"Fares":[{"TicketType":1,"FareClass":1,"CabinClass":1,"Price":378},{"TicketType":1,"FareClass":3,"CabinClass":1,"Price":189},{"TicketType":1,"FareClass":4,"CabinClass":1,"Price":189},{"TicketType":1,"FareClass":5,"CabinClass":1,"Price":189},{"TicketType":1,"FareClass":7,"CabinClass":1,"Price":189}]},{"TrainType":10,"Fares":[{"TicketType":1,"FareClass":1,"CabinClass":1,"Price":378},{"TicketType":1,"FareClass":3,"CabinClass":1,"Price":189},{"TicketType":1,"FareClass":4,"CabinClass":1,"Price":189},{"TicketType":1,"FareClass":5,"CabinClass":1,"Price":189},{"TicketType":1,"FareClass":7,"CabinClass":1,"Price":189}]},{"TrainType":6,"Fares":[{"TicketType":1,"FareClass":1,"CabinClass":1,"Price":378},{"TicketType":1,"FareClass":3,"CabinClass":1,"Price":189},{"TicketType":1,"FareClass":4,"CabinClass":1,"Price":189},{"TicketType":1,"FareClass":5,"CabinClass":1,"Price":189},{"TicketType":1,"FareClass":7,"CabinClass":1,"Price":189}]},{"TrainType":7,"Fares":[{"TicketType":1,"FareClass":1,"CabinClass":1,"Price":215},{"TicketType":1,"FareClass":3,"CabinClass":1,"Price":108},{"TicketType":1,"FareClass":4,"CabinClass":1,"Price":108},{"TicketType":1,"FareClass":5,"CabinClass":1,"Price":108},{"TicketType":1,"FareClass":7,"CabinClass":1,"Price":108}]},{"TrainType":11,"Fares":[{"TicketType":1,"FareClass":1,"CabinClass":1,"Price":1713},{"TicketType":1,"FareClass":3,"CabinClass":1,"Price":857},{"TicketType":1,"FareClass":4,"CabinClass":1,"Price":857},{"TicketType":1,"FareClass":5,"CabinClass":1,"Price":857},{"TicketType":1,"FareClass":7,"CabinClass":1,"Price":857}]},{"TrainType":1,"Fares":[{"TicketType":1,"FareClass":1,"CabinClass":1,"Price":1713},{"TicketType":1,"FareClass":3,"CabinClass":1,"Price":857},{"TicketType":1,"FareClass":4,"CabinClass":1,"Price":857},{"TicketType":1,"FareClass":5,"CabinClass":1,"Price":857},{"TicketType":1,"FareClass":7,"CabinClass":1,"Price":857}]},{"TrainType":2,"Fares":[{"TicketType":1,"FareClass":1,"CabinClass":1,"Price":1713},{"TicketType":1,"FareClass":3,"CabinClass":1,"Price":857},{"TicketType":1,"FareClass":4,"CabinClass":1,"Price":857},{"TicketType":1,"FareClass":5,"CabinClass":1,"Price":857},{"TicketType":1,"FareClass":7,"CabinClass":1,"Price":857}]},{"TrainType":3,"Fares":[{"TicketType":1,"FareClass":1,"CabinClass":1,"Price":1713},{"TicketType":1,"FareClass":3,"CabinClass":1,"Price":857},{"TicketType":1,"FareClass":4,"CabinClass":1,"Price":857},{"TicketType":1,"FareClass":5,"CabinClass":1,"Price":857},{"TicketType":1,"FareClass":7,"CabinClass":1,"Price":857}]},{"TrainType":4,"Fares":[{"TicketType":1,"FareClass":1,"CabinClass":1,"Price":1327},{"TicketType":1,"FareClass":3,"CabinClass":1,"Price":664},{"TicketType":1,"FareClass":4,"CabinClass":1,"Price":664},{"TicketType":1,"FareClass":5,"CabinClass":1,"Price":664},{"TicketType":1,"FareClass":7,"CabinClass":1,"Price":664}]},{"TrainType":5,"Fares":[{"TicketType":1,"FareClass":1,"CabinClass":1,"Price":1111},{"TicketType":1,"FareClass":3,"CabinClass":1,"Price":556},{"TicketType":1,"FareClass":4,"CabinClass":1,"Price":556},{"TicketType":1,"FareClass":5,"CabinClass":1,"Price":556},{"TicketType":1,"FareClass":7,"CabinClass":1,"Price":556}]},{"TrainType":10,"Fares":[{"TicketType":1,"FareClass":1,"CabinClass":1,"Price":1111},{"TicketType":1,"FareClass":3,"CabinClass":1,"Price":556},{"TicketType":1,"FareClass":4,"CabinClass":1,"Price":556},{"TicketType":1,"FareClass":5,"CabinClass":1,"Price":556},{"TicketType":1,"FareClass":7,"CabinClass":1,"Price":556}]},{"TrainType":6,"Fares":[{"TicketType":1,"FareClass":1,"CabinClass":1,"Price":1111},{"TicketType":1,"FareClass":3,"CabinClass":1,"Price":556},{"TicketType":1,"FareClass":4,"CabinClass":1,"Price":556},{"TicketType":1,"FareClass":5,"CabinClass":1,"Price":556},{"TicketType":1,"FareClass":7,"CabinClass":1,"Price":556}]},{"TrainType":7,"Fares":[{"TicketType":1,"FareClass":1,"CabinClass":1,"Price":749},{"TicketType":1,"FareClass":3,"CabinClass":1,"Price":375},{"TicketType":1,"FareClass":4,"CabinClass":1,"Price":375},{"TicketType":1,"FareClass":5,"CabinClass":1,"Price":375},{"TicketType":1,"FareClass":7,"CabinClass":1,"Price":375}]}]}