{"TrainInfo":{"TrainNo":"1811","RouteID":"","Direction":1,"TrainTypeID":"1131","TrainTypeCode":"6","TrainTypeName":{"Zh_tw":"區間","En":"Local Train"},"TripHeadSign":"往竹中","StartingStationID":"1208","StartingStationName":{"Zh_tw":"內灣","En":"Neiwan"},"EndingStationID":"1193","EndingStationName":{"Zh_tw":"竹中","En":"Zhuzhong"},"OverNightStationID":"","TripLine":0,"WheelChairFlag":0,"PackageServiceFlag":0,"DiningFlag":0,"BreastFeedFlag":0,"BikeFlag":0,"CarFlag":0,"DailyFlag":1,"ExtraTrainFlag":0,"SuspendedFlag":0,"Note":"每日行駛。"},"StopTimes":[{"StopSequence":1,"StationID":"1208","StationName":{"Zh_tw":"內灣","En":"Neiwan"},"ArrivalTime":"09:47","DepartureTime":"09:47","SuspendedFlag":0},{"StopSequence":2,"StationID":"1207","StationName":{"Zh_tw":"富貴","En":"Fugui"},"ArrivalTime":"09:51","DepartureTime":"09:51","SuspendedFlag":0},{"StopSequence":3,"StationID":"1206","StationName":{"Zh_tw":"合興","En":"Hexing"},"ArrivalTime":"09:55","DepartureTime":"09:55","SuspendedFlag":0},{"StopSequence":4,"StationID":"1205","StationName":{"Zh_tw":"九讚頭","En":"Jiuzantou"},"ArrivalTime":"09:59","DepartureTime":"10:00","SuspendedFlag":0},{"StopSequence":5,"StationID":"1204","StationName":{"Zh_tw":"橫山","En":"Hengshan"},"ArrivalTime":"10:03","DepartureTime":"10:04","SuspendedFlag":0},{"StopSequence":6,"StationID":"1203","StationName":{"Zh_tw":"竹東","En":"Zhudong"},"ArrivalTime":"10:09","DepartureTime":"10:12","SuspendedFlag":0},{"StopSequence":7,"StationID":"1202","StationName":{"Zh_tw":"榮華","En":"Ronghua"},"ArrivalTime":"10:15","DepartureTime":"10:16","SuspendedFlag":0},{"StopSequence":8,"StationID":"1201","StationName":{"Zh_tw":"上員","En":"Shangyuan"},"ArrivalTime":"10:22","DepartureTime":"10:22","SuspendedFlag":0},{"StopSequence":9,"StationID":"1193","StationName":{"Zh_tw":"竹中","En":"Zhuzhong"},"ArrivalTime":"10:27","DepartureTime":"10:28","SuspendedFlag":0}]}