{"OriginStationID":"3320","OriginStationName":{"Zh_tw":"大慶","En":"Daqing"},"DestinationStationID":"4272","DestinationStationName":{"Zh_tw":"沙崙","En":"Shalun"},"TrainFares":[{"TrainType":11,"Fares":[{"TicketType":1,"FareClass":1,"CabinClass":1,"Price":1747},{"TicketType":1,"FareClass":3,"CabinClass":1,"Price":874},{"TicketType":1,"FareClass":4,"CabinClass":1,"Price":874},{"TicketType":1,"FareClass":5,"CabinClass":1,"Price":874},{"TicketType":1,"FareClass":7,"CabinClass":1,"Price":874}]},{"TrainType":1,"Fares":[{"TicketType":1,"FareClass":1,"CabinClass":1,"Price":1747},{"TicketType":1,"FareClass":3,"CabinClass":1,"Price":874},{"TicketType":1,"FareClass":4,"CabinClass":1,"Price":874},{"TicketType":1,"FareClass":5,"CabinClass":1,"Price":874},{"TicketType":1,"FareClass":7,"CabinClass":1,"Price":874}]},{"TrainType":2,"Fares":[{"TicketType":1,"FareClass":1,"CabinClass":1,"Price":1747},{"TicketType":1,"FareClass":3,"CabinClass":1,"Price":874},{"TicketType":1,"FareClass":4,"CabinClass":1,"Price":874},{"TicketType":1,"FareClass":5,"CabinClass":1,"Price":874},{"TicketType":1,"FareClass":7,"CabinClass":1,"Price":874}]},{"TrainType":3,"Fares":[{"TicketType":1,"FareClass":1,"CabinClass":1,"Price":1747},{"TicketType":1,"FareClass":3,"CabinClass":1,"Price":874},{"TicketType":1,"FareClass":4,"CabinClass":1,"Price":874},{"TicketType":1,"FareClass":5,"CabinClass":1,"Price":874},{"TicketType":1,"FareClass":7,"CabinClass":1,"Price":874}]},{"TrainType":4,"Fares":[{"TicketType":1,"FareClass":1,"CabinClass":1,"Price":1352},{"TicketType":1,"FareClass":3,"CabinClass":1,"Price":676},{"TicketType":1,"FareClass":4,"CabinClass":1,"Price":676},{"TicketType":1,"FareClass":5,"CabinClass":1,"Price":676},{"TicketType":1,"FareClass":7,"CabinClass":1,"Price":676}]},{"TrainType":5,"Fares":[{"TicketType":1,"FareClass":1,"CabinClass":1,"Price":1131},{"TicketType":1,"FareClass":3,"CabinClass":1,"Price":566},{"TicketType":1,"FareClass":4,"CabinClass":1,"Price":566},{"TicketType":1,"FareClass":5,"CabinClass":1,"Price":566},{"TicketType":1,"FareClass":7,"CabinClass":1,"Price":566}]},{"TrainType":10,"Fares":[{"TicketType":1,"FareClass":1,"CabinClass":1,"Price":1131},{"TicketType":1,"FareClass":3,"CabinClass":1,"Price":566},{"TicketType":1,"FareClass":4,"CabinClass":1,"Price":566},{"TicketType":1,"FareClass":5,"CabinClass":1,"Price":566},{"TicketType":1,"FareClass":7,"CabinClass":1,"Price":566}]},{"TrainType":6,"Fares":[{"TicketType":1,"FareClass":1,"CabinClass":1,"Price":1131},{"TicketType":1,"FareClass":3,"CabinClass":1,"Price":566},{"TicketType":1,"FareClass":4,"CabinClass":1,"Price":566},{"TicketType":1,"FareClass":5,"CabinClass":1,"Price":566},{"TicketType":1,"FareClass":7,"CabinClass":1,"Price":566}]},{"TrainType":7,"Fares":[{"TicketType":1,"FareClass":1,"CabinClass":1,"Price":763},{"TicketType":1,"FareClass":3,"CabinClass":1,"Price":382},{"TicketType":1,"FareClass":4,"CabinClass":1,"Price":382},{"TicketType":1,"FareClass":5,"CabinClass":1,"Price":382},{"TicketType":1,"FareClass":7,"CabinClass":1,"Price":382}]},{"TrainType":11,"Fares":[{"TicketType":1,"FareClass":1,"CabinClass":1,"Price":520},{"TicketType":1,"FareClass":3,"CabinClass":1,"Price":260},{"TicketType":1,"FareClass":4,"CabinClass":1,"Price":260},{"TicketType":1,"FareClass":5,"CabinClass":1,"Price":260},{"TicketType":1,"FareClass":7,"CabinClass":1,"Price":260}]},{"TrainType":1,"Fares":[{"TicketType":1,"FareClass":1,"CabinClass":1,"Price":520},{"TicketType":1,"FareClass":3,"CabinClass":1,"Price":260},{"TicketType":1,"FareClass":4,"CabinClass":1,"Price":260},{"TicketType":1,"FareClass":5,"CabinClass":1,"Price":260},{"TicketType":1,"FareClass":7,"CabinClass":1,"Price":260}]},{"TrainType":2,"Fares":[{"TicketType":1,"FareClass":1,"CabinClass":1,"Price":520},{"TicketType":1,"FareClass":3,"CabinClass":1,"Price":260},{"TicketType":1,"FareClass":4,"CabinClass":1,"Price":260},{"TicketType":1,"FareClass":5,"CabinClass":1,"Price":260},{"TicketType":1,"FareClass":7,"CabinClass":1,"Price":260}]},{"TrainType":3,"Fares":[{"TicketType":1,"FareClass":1,"CabinClass":1,"Price":520},{"TicketType":1,"FareClass":3,"CabinClass":1,"Price":260},{"TicketType":1,"FareClass":4,"CabinClass":1,"Price":260},{"TicketType":1,"FareClass":5,"CabinClass":1,"Price":260},{"TicketType":1,"FareClass":7,"CabinClass":1,"Price":260}]},{"TrainType":4,"Fares":[{"TicketType":1,"FareClass":1,"CabinClass":1,"Price":404},{"TicketType":1,"FareClass":3,"CabinClass":1,"Price":202},{"TicketType":1,"FareClass":4,"CabinClass":1,"Price":202},{"TicketType":1,"FareClass":5,"CabinClass":1,"Price":202},{"TicketType":1,"FareClass":7,"CabinClass":1,"Price":202}]},{"TrainType":5,"Fares":[{"TicketType":1,"FareClass":1,"CabinClass":1,"Price":339},{"TicketType":1,"FareClass":3,"CabinClass":1,"Price":170},{"TicketType":1,"FareClass":4,"CabinClass":1,"Price":170},{"TicketType":1,"FareClass":5,"CabinClass":1,"Price":170},{"TicketType":1,"FareClass":7,"CabinClass":1,"Price":170}]},{"TrainType":10,"Fares":[{"TicketType":1,"FareClass":1,"CabinClass":1,"Price":339},{"TicketType":1,"FareClass":3,"CabinClass":1,"Price":170},{"TicketType":1,"FareClass":4,"CabinClass":1,"Price":170},{"TicketType":1,"FareClass":5,"CabinClass":1,"Price":170},{"TicketType":1,"FareClass":7,"CabinClass":1,"Price":170}]},{"TrainType":6,"Fares":[{"TicketType":1,"FareClass":1,"CabinClass":1,"Price":339},{"TicketType":1,"FareClass":3,"CabinClass":1,"Price":170},{"TicketType":1,"FareClass":4,"CabinClass":1,"Price":170},{"TicketType":1,"FareClass":5,"CabinClass":1,"Price":170},{"TicketType":1,"FareClass":7,"CabinClass":1,"Price":170}]},{"TrainType":7,"Fares":[{"TicketType":1,"FareClass":1,"CabinClass":1,"Price":189},{"TicketType":1,"FareClass":3,"CabinClass":1,"Price":95},{"TicketType":1,"FareClass":4,"CabinClass":1,"Price":95},{"TicketType":1,"FareClass":5,"CabinClass":1,"Price":95},{"TicketType":1,"FareClass":7,"CabinClass":1,"Price":95}]}]}