{"OriginStationID":"3433","OriginStationName":{"Zh_tw":"龍泉","En":"Longquan"},"DestinationStationID":"4180","DestinationStationName":{"Zh_tw":"南科","En":"Nanke"},"Direction":1,"TrainType":7,"Fares":[{"TicketType":1,"FareClass":1,"CabinClass":1,"Price":136},{"TicketType":1,"FareClass":3,"CabinClass":1,"Price":68},{"TicketType":1,"FareClass":4,"CabinClass":1,"Price":68},{"TicketType":1,"FareClass":5,"CabinClass":1,"Price":68},{"TicketType":1,"FareClass":7,"CabinClass":1,"Price":68}],"TravelDistance":109.9}