{"OriginStationID":"4070","OriginStationName":{"Zh_tw":"嘉北","En":"Jiabei"},"DestinationStationID":"7334","DestinationStationName":{"Zh_tw":"嶺腳","En":"Lingjiao"},"Direction":1,"TrainType":7,"Fares":[{"TicketType":1,"FareClass":1,"CabinClass":1,"Price":638},{"TicketType":1,"FareClass":3,"CabinClass":1,"Price":320},{"TicketType":1,"FareClass":4,"CabinClass":1,"Price":320},{"TicketType":1,"FareClass":5,"CabinClass":1,"Price":320},{"TicketType":1,"FareClass":7,"CabinClass":1,"Price":320}],"TravelDistance":584.8}