{"OriginStationID":"0990","OriginStationName":{"Zh_tw":"松山","En":"Songshan"},"DestinationStationID":"7160","DestinationStationName":{"Zh_tw":"羅東","En":"Luodong"},"Direction":1,"TrainType":7,"Fares":[{"TicketType":1,"FareClass":1,"CabinClass":1,"Price":824},{"TicketType":1,"FareClass":3,"CabinClass":1,"Price":412},{"TicketType":1,"FareClass":4,"CabinClass":1,"Price":412},{"TicketType":1,"FareClass":5,"CabinClass":1,"Price":412},{"TicketType":1,"FareClass":7,"CabinClass":1,"Price":412}],"TravelDistance":777.6}