{"OriginStationID":"1160","OriginStationName":{"Zh_tw":"湖口","En":"Hukou"},"DestinationStationID":"1201","DestinationStationName":{"Zh_tw":"上員","En":"Shangyuan"},"Direction":1,"TrainType":7,"Fares":[{"TicketType":1,"FareClass":1,"CabinClass":1,"Price":36},{"TicketType":1,"FareClass":3,"CabinClass":1,"Price":18},{"TicketType":1,"FareClass":4,"CabinClass":1,"Price":18},{"TicketType":1,"FareClass":5,"CabinClass":1,"Price":18},{"TicketType":1,"FareClass":7,"CabinClass":1,"Price":18}],"TravelDistance":24.6}